llama_index/llms/vllm/__init__.py
llama_index/llms/vllm/base.py
llama_index/llms/vllm/utils.py
llama_index_llms_vllm-0.6.2.dist-info/METADATA
llama_index_llms_vllm-0.6.2.dist-info/WHEEL
llama_index_llms_vllm-0.6.2.dist-info/licenses/LICENSE
llama_index_llms_vllm-0.6.2.dist-info/RECORD
