Metadata-Version: 2.4
Name: llama-index-llms-vllm
Version: 0.6.2
Summary: llama-index llms vllm integration
Author-email: Your Name <you@example.com>
License-Expression: MIT
License-File: LICENSE
Requires-Python: <4.0,>=3.9
Requires-Dist: llama-index-core<0.15,>=0.13.0
